utools/__init__.py
utools/bin/Readme.md
utools/bin/__init__.py
utools/bin/advpng
utools/bin/gifsicle
utools/bin/guetzli
utools/bin/jpegoptim
utools/bin/jpegtran
utools/bin/oxipng
utools/bin/pngcrush
utools/bin/pngout
utools/bin/pngquant
utools/bin/pngquant-openmp
utools/bin/svgcleaner
utools/bin/svgo.js
utools/bin/zopflipng
utools/tools/App.py
utools/tools/__init__.py
utools/tools/common/__init__.py
utools/tools/common/filemanager.py
utools/tools/image/__init__.py
utools/tools/image/imageopt.py
utools/tools/image/optconfig.py
utools.dev-0.1.1.post1.dist-info/METADATA
utools.dev-0.1.1.post1.dist-info/RECORD
utools.dev-0.1.1.post1.dist-info/WHEEL
utools.dev-0.1.1.post1.dist-info/entry_points.txt
utools.dev-0.1.1.post1.dist-info/top_level.txt
