Metadata-Version: 2.1
Name: utools.dev
Version: 0.1.1.post1
Summary: 开发工具集
Home-page: UNKNOWN
Author: zauther
Author-email: zauther@qq.com
License: MIT
Platform: mac osx
Classifier: Development Status :: 3 - Alpha
Classifier: Intended Audience :: Developers
Classifier: Topic :: Software Development :: Build Tools
Classifier: License :: OSI Approved :: MIT License
Classifier: Programming Language :: Python :: 3.5
